<root>
<mobilebase>
	<cadEngine>
		<git>https://github.com/madhephaestus/6dofServoArm.git</git>
		<file>Bowler/MediumCad.groovy</file>
	</cadEngine>
	<driveEngine>
		<git>https://github.com/madhephaestus/6dofServoArm.git</git>
		<file>walking.groovy</file>
	</driveEngine>

<name>Standard6dof</name>
<appendage>

<name>Standard6dofArm</name>
	<cadEngine>
		<git>https://github.com/madhephaestus/6dofServoArm.git</git>
		<file>Bowler/MediumCad.groovy</file>
	</cadEngine>
	<kinematics>
		<git>https://github.com/madhephaestus/6dofServoArm.git</git>
		<file>DefaultDhSolver.groovy</file>
	</kinematics>
<link>
	<name>basePan</name>
	<deviceName>kevkat</deviceName>
	<type>hidfast</type>
	<index>1</index>
	<scale>1.0</scale>
	<upperLimit>179.0</upperLimit>
	<lowerLimit>0.0</lowerLimit>
	<upperVelocity>1.0E8</upperVelocity>
	<lowerVelocity>-1.0E8</lowerVelocity>
	<staticOffset>90.0</staticOffset>
	<deviceTheoreticalMax>180.0</deviceTheoreticalMax>
	<deviceTheoreticalMin>0.0</deviceTheoreticalMin>
	<isLatch>true</isLatch>
	<indexLatch>105.0</indexLatch>
	<isStopOnLatch>false</isStopOnLatch>
	<homingTPS>10000000</homingTPS>

	<vitamins>
		<vitamin>
			<name>electroMechanical</name>
			<type>hobbyServo</type>
			<id>towerProMG91</id>
		</vitamin>
		<vitamin>
			<name>shaft</name>
			<type>hobbyServoHorn</type>
			<id>tproSG90_1</id>
		</vitamin>

	</vitamins>
	<passive>false</passive>
	<mass>0.0302</mass>
	<centerOfMassFromCentroid>	<x>-1.5</x>
	<y>0.0</y>
	<z>0.0</z>
	<rotw>1.0</rotw>
	<rotx>0.0</rotx>
	<roty>0.0</roty>
	<rotz>0.0</rotz></centerOfMassFromCentroid>
	<imuFromCentroid>	<x>0.0</x>
	<y>0.0</y>
	<z>0.0</z>
	<rotw>1.0</rotw>
	<rotx>-0.0</rotx>
	<roty>-0.0</roty>
	<rotz>-0.0</rotz></imuFromCentroid>

	<DHParameters>
		<Delta>0.0</Delta>
		<Theta>0.01</Theta>
		<Radius>28.575</Radius>
		<Alpha>-89.97</Alpha>
	</DHParameters>

</link>
<link>
	<name>baseTilt</name>
	<deviceName>kevkat</deviceName>
	<type>hidfast</type>
	<index>2</index>
	<scale>1.0</scale>
	<upperLimit>180.0</upperLimit>
	<lowerLimit>0.0</lowerLimit>
	<upperVelocity>1.0E8</upperVelocity>
	<lowerVelocity>-1.0E8</lowerVelocity>
	<staticOffset>90.0</staticOffset>
	<deviceTheoreticalMax>180.0</deviceTheoreticalMax>
	<deviceTheoreticalMin>0.0</deviceTheoreticalMin>
	<isLatch>true</isLatch>
	<indexLatch>97.0</indexLatch>
	<isStopOnLatch>false</isStopOnLatch>
	<homingTPS>10000000</homingTPS>

	<vitamins>
		<vitamin>
			<name>electroMechanical</name>
			<type>hobbyServo</type>
			<id>towerProMG91</id>
		</vitamin>
		<vitamin>
			<name>shaft</name>
			<type>hobbyServoHorn</type>
			<id>tproSG90_1</id>
		</vitamin>

	</vitamins>
	<passive>false</passive>
	<mass>0.0299</mass>
	<centerOfMassFromCentroid>	<x>-13.21</x>
	<y>0.0</y>
	<z>0.0</z>
	<rotw>1.0</rotw>
	<rotx>0.0</rotx>
	<roty>0.0</roty>
	<rotz>0.0</rotz></centerOfMassFromCentroid>
	<imuFromCentroid>	<x>0.0</x>
	<y>0.0</y>
	<z>0.0</z>
	<rotw>1.0</rotw>
	<rotx>-0.0</rotx>
	<roty>-0.0</roty>
	<rotz>-0.0</rotz></imuFromCentroid>

	<DHParameters>
		<Delta>0.0</Delta>
		<Theta>-90.0</Theta>
		<Radius>50.8</Radius>
		<Alpha>0.01</Alpha>
	</DHParameters>

</link>
<link>
	<name>elbow</name>
	<deviceName>kevkat</deviceName>
	<type>hidfast</type>
	<index>0</index>
	<scale>1.0</scale>
	<upperLimit>180.0</upperLimit>
	<lowerLimit>0.0</lowerLimit>
	<upperVelocity>1.0E8</upperVelocity>
	<lowerVelocity>-1.0E8</lowerVelocity>
	<staticOffset>90.0</staticOffset>
	<deviceTheoreticalMax>180.0</deviceTheoreticalMax>
	<deviceTheoreticalMin>0.0</deviceTheoreticalMin>
	<isLatch>true</isLatch>
	<indexLatch>145.0</indexLatch>
	<isStopOnLatch>false</isStopOnLatch>
	<homingTPS>10000000</homingTPS>

	<vitamins>
		<vitamin>
			<name>electroMechanical</name>
			<type>hobbyServo</type>
			<id>towerProMG91</id>
		</vitamin>
		<vitamin>
			<name>shaft</name>
			<type>hobbyServoHorn</type>
			<id>tproSG90_1</id>
		</vitamin>

	</vitamins>
	<passive>false</passive>
	<mass>0.0091</mass>
	<centerOfMassFromCentroid>	<x>-32.31</x>
	<y>-10.0</y>
	<z>0.0</z>
	<rotw>1.0</rotw>
	<rotx>0.0</rotx>
	<roty>0.0</roty>
	<rotz>0.0</rotz></centerOfMassFromCentroid>
	<imuFromCentroid>	<x>0.0</x>
	<y>0.0</y>
	<z>0.0</z>
	<rotw>1.0</rotw>
	<rotx>-0.0</rotx>
	<roty>-0.0</roty>
	<rotz>-0.0</rotz></imuFromCentroid>

	<DHParameters>
		<Delta>0.0</Delta>
		<Theta>90.01</Theta>
		<Radius>47.86</Radius>
		<Alpha>0.01</Alpha>
	</DHParameters>

</link>

<ZframeToRAS
>	<x>0.0</x>
	<y>0.0</y>
	<z>0.0</z>
	<rotw>1.0</rotw>
	<rotx>-0.0</rotx>
	<roty>-0.0</roty>
	<rotz>-0.0</rotz>
</ZframeToRAS>

<baseToZframe>
	<x>0.0</x>
	<y>0.0</y>
	<z>0.0</z>
	<rotw>1.0</rotw>
	<rotx>-0.0</rotx>
	<roty>-0.0</roty>
	<rotz>-0.0</rotz>
</baseToZframe>

</appendage>

<ZframeToRAS>
	<x>0.0</x>
	<y>0.0</y>
	<z>0.0</z>
	<rotw>1.0</rotw>
	<rotx>-0.0</rotx>
	<roty>-0.0</roty>
	<rotz>-0.0</rotz>
</ZframeToRAS>

<baseToZframe>
	<x>0.0</x>
	<y>0.0</y>
	<z>0.0</z>
	<rotw>1.0</rotw>
	<rotx>-0.0</rotx>
	<roty>-0.0</roty>
	<rotz>-0.0</rotz>
</baseToZframe>
	<mass>0.001</mass>
	<centerOfMassFromCentroid>	<x>0.0</x>
	<y>0.0</y>
	<z>0.0</z>
	<rotw>1.0</rotw>
	<rotx>0.0</rotx>
	<roty>0.0</roty>
	<rotz>0.0</rotz></centerOfMassFromCentroid>
	<imuFromCentroid>	<x>0.0</x>
	<y>0.0</y>
	<z>0.0</z>
	<rotw>1.0</rotw>
	<rotx>-0.0</rotx>
	<roty>-0.0</roty>
	<rotz>-0.0</rotz></imuFromCentroid>

<vitamins>

</vitamins>

</mobilebase>

</root>